multiserver/multiserver.py
router/router.py
samples/callable_handler.py
samples/clock.py
samples/date_time_simple.py
samples/delayed_server.py
samples/digest_authentication.py
samples/env.py
samples/exception.py
samples/function_app.py
samples/function_app2.py
samples/generator.py
samples/getset.py
samples/hello_time.py
samples/hello_world.py
samples/hello_world_function.py
samples/hello_world_relpath.py
samples/hello_world_wsgi.py
samples/http_server.py
samples/https.py
samples/https_server.py
samples/lambda_app.py
samples/make_response.py
samples/nested_handlers.py
samples/permissions.py
samples/post.py
samples/post_client.py
samples/post_print.py
samples/post_receiver.py
samples/redirect.py
samples/relpath.py
samples/robots.py
samples/sanitize.py
samples/slow_server.py
samples/standalone_server.py
samples/standalone_session_app.py
samples/standalone_threaded_app.py
samples/static_server.py
samples/strict_handler.py
samples/templates.py
samples/test.py
samples/threads_1.py
samples/threads_2.py
samples/threads_context.py
samples/time_args.py
samples/time_count.py
samples/time_count_thread_safe.py
samples/time_handlers.py
samples/time_hello_split.py
samples/time_index.py
samples/time_returns.py
samples/time_server.py
samples/uwsgi_app.py
samples/wp_test.py
webpie/HTTPServer.py
webpie/Version.py
webpie/WPApp.py
webpie/WPSessionApp.py
webpie/__init__.py
webpie/py3.py
webpie/sanitizers.py
webpie/uid.py
webpie/yaml_expand.py
webpie/logs/__init__.py
webpie/logs/log_file.py
webpie/logs/logs.py
webpie/webob/__init__.py
webpie/webob/acceptparse.py
webpie/webob/byterange.py
webpie/webob/cachecontrol.py
webpie/webob/client.py
webpie/webob/compat.py
webpie/webob/cookies.py
webpie/webob/datetime_utils.py
webpie/webob/dec.py
webpie/webob/descriptors.py
webpie/webob/etag.py
webpie/webob/exc.py
webpie/webob/headers.py
webpie/webob/multidict.py
webpie/webob/request.py
webpie/webob/response.py
webpie/webob/static.py
webpie/webob/util.py
webpie-5.16.3.dist-info/LICENSE
webpie-5.16.3.dist-info/METADATA
webpie-5.16.3.dist-info/WHEEL
webpie-5.16.3.dist-info/entry_points.txt
webpie-5.16.3.dist-info/top_level.txt
webpie-5.16.3.dist-info/RECORD
