Metadata-Version: 2.1
Name: webpie
Version: 5.16.3
Summary: A set of useful tools built on top of standard Python threading module
Home-page: https://webpie.github.io/
Author: Igor Mandrichenko
Author-email: igorvm@gmail.com
License: BSD 3-clause
Keywords: web service,wsgi,web application
Platform: UNKNOWN
Classifier: Operating System :: POSIX
Classifier: Topic :: Internet :: WWW/HTTP :: WSGI :: Server
Classifier: Topic :: Internet :: WWW/HTTP :: WSGI :: Middleware
Classifier: Topic :: Internet :: WWW/HTTP :: HTTP Servers
Classifier: Topic :: Internet :: WWW/HTTP :: WSGI :: Application
Classifier: Programming Language :: Python
Classifier: Programming Language :: Python :: 3
Classifier: Programming Language :: Python :: 3.7
Classifier: Programming Language :: Python :: 3.8
Classifier: Development Status :: 5 - Production/Stable
Classifier: License :: OSI Approved :: BSD License
Classifier: Intended Audience :: Developers
Requires-Dist: pythreader (>=2.8.2)
